fabric_scheduler/__init__.py
fabric_scheduler/core/__init__.py
fabric_scheduler/core/_artifacts.py
fabric_scheduler/core/_core.py
fabric_scheduler/core/_schedules.py
fabric_scheduler/core/_workspace.py
fabric_scheduler/models/__init__.py
fabric_scheduler/models/_models.py
fabric_scheduler/utils/__init__.py
fabric_scheduler/utils/_api_utils.py
fabric_scheduler/utils/_constants.py
fabric_scheduler/utils/_csv_utils.py
fabric_scheduler/utils/_date_utils.py
fabric_scheduler/utils/_display_utils.py
fabric_scheduler-1.0.1.dist-info/licenses/LICENSE.txt
fabric_scheduler-1.0.1.dist-info/METADATA
fabric_scheduler-1.0.1.dist-info/WHEEL
fabric_scheduler-1.0.1.dist-info/top_level.txt
fabric_scheduler-1.0.1.dist-info/RECORD
