Metadata-Version: 2.4
Name: fabric_scheduler
Version: 1.0.1
Summary: Effortlessly automate and manage schedules for Microsoft Fabric artifacts using a user-friendly Python API.
Home-page: https://github.com/shahlaukik/fabric_scheduler
Author: Laukik Shah
Author-email: 78136178+shahlaukik@users.noreply.github.com
License: MIT
Project-URL: Documentation, https://fabric-scheduler.readthedocs.io/
Project-URL: Source, https://github.com/shahlaukik/fabric_scheduler/
Project-URL: Changelog, https://fabric-scheduler.readthedocs.io/en/latest/changelog.html
Project-URL: Tracker, https://github.com/shahlaukik/fabric_scheduler/issues
Keywords: Microsoft Fabric,Fabric Automation,Pipelines,Dataflows,Notebooks,Scheduling,Workspace Management,Deployment,Data Engineering,DevOps
Platform: any
Classifier: Development Status :: 5 - Production/Stable
Classifier: Programming Language :: Python
Classifier: Topic :: Software Development :: Libraries
Classifier: Topic :: Software Development :: Libraries :: Python Modules
Classifier: Topic :: Database
Classifier: Topic :: System :: Systems Administration
Classifier: Topic :: Office/Business
Classifier: Topic :: Office/Business :: Scheduling
Classifier: Topic :: Scientific/Engineering
Classifier: Topic :: Utilities
Classifier: Intended Audience :: Developers
Classifier: Intended Audience :: Information Technology
Classifier: Intended Audience :: System Administrators
Classifier: Intended Audience :: Science/Research
Classifier: Intended Audience :: Other Audience
Classifier: Operating System :: OS Independent
License-File: LICENSE.txt
Requires-Dist: importlib-metadata; python_version < "3.8"
Requires-Dist: pandas>=2.0.0
Requires-Dist: semantic-link-sempy>=0.10.2
Provides-Extra: testing
Requires-Dist: setuptools; extra == "testing"
Requires-Dist: pytest; extra == "testing"
Requires-Dist: pytest-cov; extra == "testing"
Provides-Extra: dev
Requires-Dist: tox>=4.0.0; extra == "dev"
Requires-Dist: black>=23.0.0; extra == "dev"
Requires-Dist: flake8>=6.0.0; extra == "dev"
Requires-Dist: mypy>=1.0.0; extra == "dev"
Requires-Dist: pre-commit>=3.5.0; extra == "dev"
Requires-Dist: ruff>=0.1.0; extra == "dev"
Requires-Dist: isort>=5.12.0; extra == "dev"
Dynamic: license-file
